chatchat/__init__.py
chatchat/cli.py
chatchat/data/knowledge_base/samples/content/test_files/langchain-ChatGLM_closed.csv
chatchat/data/knowledge_base/samples/content/test_files/langchain-ChatGLM_closed.xlsx
chatchat/data/knowledge_base/samples/content/test_files/langchain-ChatGLM_open.csv
chatchat/data/knowledge_base/samples/content/test_files/langchain-ChatGLM_open.xlsx
chatchat/data/knowledge_base/samples/content/test_files/langchain.pdf
chatchat/data/knowledge_base/samples/content/test_files/test.txt
chatchat/data/knowledge_base/samples/content/分布式训练技术原理.md
chatchat/data/knowledge_base/samples/content/大模型应用技术原理.md
chatchat/data/knowledge_base/samples/content/大模型技术栈-实战与应用.md
chatchat/data/knowledge_base/samples/content/大模型技术栈-算法与原理.md
chatchat/data/knowledge_base/samples/content/大模型指令对齐训练原理.md
chatchat/data/knowledge_base/samples/content/大模型推理优化策略.md
chatchat/data/nltk_data/corpora/cmudict/README
chatchat/data/nltk_data/corpora/cmudict/cmudict
chatchat/data/nltk_data/taggers/averaged_perceptron_tagger/averaged_perceptron_tagger.pickle
chatchat/data/nltk_data/tokenizers/punkt/PY3/README
chatchat/data/nltk_data/tokenizers/punkt/PY3/czech.pickle
chatchat/data/nltk_data/tokenizers/punkt/PY3/danish.pickle
chatchat/data/nltk_data/tokenizers/punkt/PY3/dutch.pickle
chatchat/data/nltk_data/tokenizers/punkt/PY3/english.pickle
chatchat/data/nltk_data/tokenizers/punkt/PY3/estonian.pickle
chatchat/data/nltk_data/tokenizers/punkt/PY3/finnish.pickle
chatchat/data/nltk_data/tokenizers/punkt/PY3/french.pickle
chatchat/data/nltk_data/tokenizers/punkt/PY3/german.pickle
chatchat/data/nltk_data/tokenizers/punkt/PY3/greek.pickle
chatchat/data/nltk_data/tokenizers/punkt/PY3/italian.pickle
chatchat/data/nltk_data/tokenizers/punkt/PY3/malayalam.pickle
chatchat/data/nltk_data/tokenizers/punkt/PY3/norwegian.pickle
chatchat/data/nltk_data/tokenizers/punkt/PY3/polish.pickle
chatchat/data/nltk_data/tokenizers/punkt/PY3/portuguese.pickle
langchain_chatchat-0.3.1.3.dist-info/METADATA
langchain_chatchat-0.3.1.3.dist-info/WHEEL
langchain_chatchat-0.3.1.3.dist-info/entry_points.txt
langchain_chatchat-0.3.1.3.dist-info/RECORD
