Metadata-Version: 2.1
Name: langchain-chatchat
Version: 0.3.1.3
Summary: Langchain-Chatchat (formerly langchain-ChatGLM), local knowledge based LLM (like ChatGLM, Qwen and Llama) RAG and Agent app with langchain
Author: chatchat
Requires-Python: >=3.8, !=2.7.*, !=3.0.*, !=3.1.*, !=3.2.*, !=3.3.*, !=3.4.*, !=3.5.*, !=3.6.*, !=3.7.*, !=3.12.*
Classifier: Programming Language :: Python :: 3
Classifier: Programming Language :: Python :: 3.9
Classifier: Programming Language :: Python :: 3.10
Classifier: Programming Language :: Python :: 3.11
Provides-Extra: extended-testing
Provides-Extra: ollama
Provides-Extra: xinference
Provides-Extra: zhipuai
Requires-Dist: PyMuPDF (>=1.23.16,<1.24.0)
Requires-Dist: SQLAlchemy (>=2.0.25,<2.1.0)
Requires-Dist: elasticsearch ; extra == "extended-testing"
Requires-Dist: faiss-cpu (>=1.7.4,<1.8.0)
Requires-Dist: fastapi (>=0.109.2,<0.110.0)
Requires-Dist: httpx[brotli,http2,socks] (>=0.25.2)
Requires-Dist: jieba (==0.42.1)
Requires-Dist: langchain (==0.1.17) ; python_full_version >= "3.8.1" and python_full_version != "3.9.7" and python_version < "3.12"
Requires-Dist: langchain-community (==0.0.36)
Requires-Dist: langchain-experimental (==0.0.58)
Requires-Dist: langchain-openai (==0.0.6) ; python_full_version >= "3.8.1" and python_full_version != "3.9.7" and python_version < "3.12"
Requires-Dist: langchainhub (==0.1.14)
Requires-Dist: loguru (>=0.7.2,<0.8.0)
Requires-Dist: markdownify (>=0.11.6)
Requires-Dist: memoization (==0.4.0)
Requires-Dist: networkx (==3.1)
Requires-Dist: nltk (>=3.8.1,<3.9.0)
Requires-Dist: numexpr (>=1)
Requires-Dist: numpy (>=1.24.4,<1.25.0)
Requires-Dist: opencv-python (==4.10.0.84)
Requires-Dist: openpyxl (==3.1.4)
Requires-Dist: pandas (>=1,<2)
Requires-Dist: pathlib (>=1.0.1,<1.1.0)
Requires-Dist: pydantic (>=2.7.4,<2.8.0)
Requires-Dist: pydantic_settings (==2.3.4)
Requires-Dist: pyjwt (>=2.8.0,<2.9.0)
Requires-Dist: pymysql (>=1.1.0,<2.0.0)
Requires-Dist: python-docx (==1.1.2)
Requires-Dist: python-magic-bin ; sys_platform == "win32"
Requires-Dist: python-multipart (==0.0.9)
Requires-Dist: rank_bm25 (==0.2.2)
Requires-Dist: rapidocr_onnxruntime (>=1.3.8,<1.4.0)
Requires-Dist: requests (>=2.31.0,<2.32.0)
Requires-Dist: ruamel_yaml (==0.18.6)
Requires-Dist: sse_starlette (>=1.8.2,<1.9.0)
Requires-Dist: streamlit (==1.34.0)
Requires-Dist: streamlit-aggrid (==1.0.5)
Requires-Dist: streamlit-antd-components (==0.3.1)
Requires-Dist: streamlit-chatbox (==1.1.12.post4)
Requires-Dist: streamlit-extras (==0.4.2)
Requires-Dist: streamlit-modal (==0.1.0)
Requires-Dist: streamlit-option-menu (==0.3.12)
Requires-Dist: streamlit-paste-button (==0.1.2)
Requires-Dist: strsimpy (>=0.2.1)
Requires-Dist: tqdm (>=4.66.1)
Requires-Dist: unstructured (>=0.11.0,<0.12.0)
Requires-Dist: uvicorn (>=0.27.0.post1)
Requires-Dist: websockets (>=12.0)
Requires-Dist: xinference_client (>=0.13.0,<0.14.0) ; extra == "xinference"
Requires-Dist: zhipuai (>=2.1.0,<3.0.0) ; extra == "zhipuai"
